vectorstack/__init__.py
vectorstack/client.py
vectorstack/error.py
vectorstack/utils.py
vectorstack/api_resources/__init__.py
vectorstack/api_resources/embeddings.py
vectorstack/objects/__init__.py
vectorstack/objects/embeddings.py
vectorstack-0.1.dist-info/LICENSE
vectorstack-0.1.dist-info/METADATA
vectorstack-0.1.dist-info/WHEEL
vectorstack-0.1.dist-info/top_level.txt
vectorstack-0.1.dist-info/RECORD
