Metadata-Version: 2.1
Name: vectorstack
Version: 0.1
Summary: VectorStack AI's Official Python Library
Author: Shreyas Saxena
Author-email: shreyas@vectorstack.ai
License: MIT
Requires-Python: >=3.8
License-File: LICENSE
Requires-Dist: requests>=2.32.3
Requires-Dist: tenacity==9.0.0
